aliceBlueWithoutApi/__init__.py
aliceBlueWithoutApi/alice.py
alicelue_brocker_wihtoutapi/__init__.py
alicelue_brocker_wihtoutapi/alice.py
fyers_withoutapi/__init__.py
fyers_withoutapi/fyers.py
zerodha_without_api/__init__.py
zerodha_without_api/zerodha.py
aliceBlueWithoutApi-0.0.1.dist-info/LICENSE
aliceBlueWithoutApi-0.0.1.dist-info/METADATA
aliceBlueWithoutApi-0.0.1.dist-info/WHEEL
aliceBlueWithoutApi-0.0.1.dist-info/top_level.txt
aliceBlueWithoutApi-0.0.1.dist-info/RECORD
